README.txt
setup.cfg
setup.py
roleplay/__init__.py
roleplay/inheritable.py
roleplay/keyword.py
roleplay/meta.py
roleplay/role.py
roleplay.egg-info/PKG-INFO
roleplay.egg-info/SOURCES.txt
roleplay.egg-info/dependency_links.txt
roleplay.egg-info/top_level.txt
