Metadata-Version: 1.0
Name: roleplay
Version: 0.1
Summary: Python does Roles
Home-page: UNKNOWN
Author: Ask Solem
Author-email: askh@opera.com
License: UNKNOWN
Platform: UNKNOWN
